{"details":{"stop_id":14674,"stop_code":14674,"stop_name":"Dempster & Dewey","stop_desc":"","stop_lat":42.04108749,"stop_lon":-87.69612067,"location_type":0,"parent_station":"","wheelchair_boarding":1},"arrivals":[{"trip_id":469101526283,"arrival_time":"14:33:19","departure_time":"14:33:19","stop_id":14674,"stop_sequence":24,"stop_headsign":"Howard","pickup_type":0,"shape_dist_traveled":17635,"route_id":206,"route_long_name":"Evanston Circulator","route_type":3},{"trip_id":469101526285,"arrival_time":"16:03:19","departure_time":"16:03:19","stop_id":14674,"stop_sequence":24,"stop_headsign":"Howard","pickup_type":0,"shape_dist_traveled":17635,"route_id":206,"route_long_name":"Evanston Circulator","route_type":3},{"trip_id":469101526287,"arrival_time":"17:19:38","departure_time":"17:19:38","stop_id":14674,"stop_sequence":24,"stop_headsign":"Howard","pickup_type":0,"shape_dist_traveled":17635,"route_id":206,"route_long_name":"Evanston Circulator","route_type":3},{"trip_id":469101526289,"arrival_time":"18:34:38","departure_time":"18:34:38","stop_id":14674,"stop_sequence":24,"stop_headsign":"Howard","pickup_type":0,"shape_dist_traveled":17635,"route_id":206,"route_long_name":"Evanston Circulator","route_type":3},{"trip_id":469101526314,"arrival_time":"15:33:19","departure_time":"15:33:19","stop_id":14674,"stop_sequence":24,"stop_headsign":"Howard","pickup_type":0,"shape_dist_traveled":17635,"route_id":206,"route_long_name":"Evanston Circulator","route_type":3},{"trip_id":469101526316,"arrival_time":"16:54:38","departure_time":"16:54:38","stop_id":14674,"stop_sequence":24,"stop_headsign":"Howard","pickup_type":0,"shape_dist_traveled":17635,"route_id":206,"route_long_name":"Evanston Circulator","route_type":3},{"trip_id":469101526318,"arrival_time":"18:09:38","departure_time":"18:09:38","stop_id":14674,"stop_sequence":24,"stop_headsign":"Howard","pickup_type":0,"shape_dist_traveled":17635,"route_id":206,"route_long_name":"Evanston Circulator","route_type":3},{"trip_id":469101526532,"arrival_time":"15:03:19","departure_time":"15:03:19","stop_id":14674,"stop_sequence":24,"stop_headsign":"Howard","pickup_type":0,"shape_dist_traveled":17635,"route_id":206,"route_long_name":"Evanston Circulator","route_type":3},{"trip_id":469101526534,"arrival_time":"16:29:38","departure_time":"16:29:38","stop_id":14674,"stop_sequence":24,"stop_headsign":"Howard","pickup_type":0,"shape_dist_traveled":17635,"route_id":206,"route_long_name":"Evanston Circulator","route_type":3},{"trip_id":469101526536,"arrival_time":"17:44:38","departure_time":"17:44:38","stop_id":14674,"stop_sequence":24,"stop_headsign":"Howard","pickup_type":0,"shape_dist_traveled":17635,"route_id":206,"route_long_name":"Evanston Circulator","route_type":3},{"trip_id":470104951084,"arrival_time":"15:05:19","departure_time":"15:05:19","stop_id":14674,"stop_sequence":24,"stop_headsign":"Howard","pickup_type":0,"shape_dist_traveled":17635,"route_id":206,"route_long_name":"Evanston Circulator","route_type":3},{"trip_id":470104951086,"arrival_time":"16:30:38","departure_time":"16:30:38","stop_id":14674,"stop_sequence":24,"stop_headsign":"Howard","pickup_type":0,"shape_dist_traveled":17635,"route_id":206,"route_long_name":"Evanston Circulator","route_type":3},{"trip_id":470104951088,"arrival_time":"17:44:38","departure_time":"17:44:38","stop_id":14674,"stop_sequence":24,"stop_headsign":"Howard","pickup_type":0,"shape_dist_traveled":17635,"route_id":206,"route_long_name":"Evanston Circulator","route_type":3},{"trip_id":470104950866,"arrival_time":"15:34:19","departure_time":"15:34:19","stop_id":14674,"stop_sequence":24,"stop_headsign":"Howard","pickup_type":0,"shape_dist_traveled":17635,"route_id":206,"route_long_name":"Evanston Circulator","route_type":3},{"trip_id":470104950868,"arrival_time":"16:54:38","departure_time":"16:54:38","stop_id":14674,"stop_sequence":24,"stop_headsign":"Howard","pickup_type":0,"shape_dist_traveled":17635,"route_id":206,"route_long_name":"Evanston Circulator","route_type":3},{"trip_id":470104950870,"arrival_time":"18:09:38","departure_time":"18:09:38","stop_id":14674,"stop_sequence":24,"stop_headsign":"Howard","pickup_type":0,"shape_dist_traveled":17635,"route_id":206,"route_long_name":"Evanston Circulator","route_type":3},{"trip_id":470104950835,"arrival_time":"14:36:19","departure_time":"14:36:19","stop_id":14674,"stop_sequence":24,"stop_headsign":"Howard","pickup_type":0,"shape_dist_traveled":17635,"route_id":206,"route_long_name":"Evanston Circulator","route_type":3},{"trip_id":470104950837,"arrival_time":"16:02:19","departure_time":"16:02:19","stop_id":14674,"stop_sequence":24,"stop_headsign":"Howard","pickup_type":0,"shape_dist_traveled":17635,"route_id":206,"route_long_name":"Evanston Circulator","route_type":3},{"trip_id":470104950839,"arrival_time":"17:19:38","departure_time":"17:19:38","stop_id":14674,"stop_sequence":24,"stop_headsign":"Howard","pickup_type":0,"shape_dist_traveled":17635,"route_id":206,"route_long_name":"Evanston Circulator","route_type":3},{"trip_id":470104950841,"arrival_time":"18:34:38","departure_time":"18:34:38","stop_id":14674,"stop_sequence":24,"stop_headsign":"Howard","pickup_type":0,"shape_dist_traveled":17635,"route_id":206,"route_long_name":"Evanston Circulator","route_type":3},{"trip_id":470105213562,"arrival_time":"14:21:03","departure_time":"14:21:03","stop_id":14674,"stop_sequence":5,"stop_headsign":"Howard","pickup_type":0,"shape_dist_traveled":2331,"route_id":206,"route_long_name":"Evanston Circulator","route_type":3},{"trip_id":470105213563,"arrival_time":"15:57:03","departure_time":"15:57:03","stop_id":14674,"stop_sequence":5,"stop_headsign":"Howard","pickup_type":0,"shape_dist_traveled":2331,"route_id":206,"route_long_name":"Evanston Circulator","route_type":3},{"trip_id":470105213564,"arrival_time":"15:47:03","departure_time":"15:47:03","stop_id":14674,"stop_sequence":5,"stop_headsign":"Howard","pickup_type":0,"shape_dist_traveled":2331,"route_id":206,"route_long_name":"Evanston Circulator","route_type":3},{"trip_id":470105213567,"arrival_time":"14:31:03","departure_time":"14:31:03","stop_id":14674,"stop_sequence":5,"stop_headsign":"Howard","pickup_type":0,"shape_dist_traveled":2331,"route_id":206,"route_long_name":"Evanston Circulator","route_type":3}]}